tclib/__init__.py
tclib/__main__.py
tclib-0.0.3.dist-info/DESCRIPTION.rst
tclib-0.0.3.dist-info/METADATA
tclib-0.0.3.dist-info/RECORD
tclib-0.0.3.dist-info/WHEEL
tclib-0.0.3.dist-info/metadata.json
tclib-0.0.3.dist-info/top_level.txt
