Metadata-Version: 2.0
Name: tclib
Version: 0.0.3
Summary: Personal library
Home-page: https://github.com/TianyiChen/tclib
Author: Tianyi Chen
Author-email: 
License: UNKNOWN
Platform: UNKNOWN
Classifier: Programming Language :: Python :: 3
Classifier: License :: OSI Approved :: MIT License
Classifier: Operating System :: POSIX :: Linux
Requires-Dist: requests
